qualitative_model_fitting/__init__.py
qualitative_model_fitting/_parser.py
qualitative_model_fitting/_runner.py
qualitative_model_fitting/_simulator.py
QualitativeModelFitting-0.0.4.dist-info/LICENCE
QualitativeModelFitting-0.0.4.dist-info/METADATA
QualitativeModelFitting-0.0.4.dist-info/WHEEL
QualitativeModelFitting-0.0.4.dist-info/top_level.txt
QualitativeModelFitting-0.0.4.dist-info/RECORD
