Metadata-Version: 2.1
Name: QualitativeModelFitting
Version: 0.0.4
Summary: UNKNOWN
Home-page: https://github.com/CiaranWelsh/QualitativeModelFitting
Author: Ciaran Welsh
Author-email: ciaran.welsh@newcastle.ac.uk
License: MIT
Keywords: SBML,antimony,tellurium,qualitative modelling
Platform: UNKNOWN
Requires-Dist: tellurium
Requires-Dist: pycotools3
Requires-Dist: pandas
Requires-Dist: numpy
Requires-Dist: lark-parser
Requires-Dist: sphinx-rtd-theme (>=0.3.1)
